velilogger.py
velilogger-1.0.1.dist-info/METADATA
velilogger-1.0.1.dist-info/WHEEL
velilogger-1.0.1.dist-info/top_level.txt
velilogger-1.0.1.dist-info/RECORD
