Metadata-Version: 2.1
Name: velilogger
Version: 1.0.1
Summary: Veli Logger
Author: Konstantine
Author-email: kdvalishvili@veli.store
